{
  "id": "memento",
  "v": "v1",
  "ts": 1732158616881,
  "signature": "s45334.189719/45334.203478",
  "data": {
    "machineId": "ed7e9ee14a81bb55ce0a3e71015a35edf5b2da712536016f50868808b5e3b2fc",
    "ts": 1732158616881,
    "log": [
      [
        1732117908324,
        0,
        "activate",
        1
      ],
      [
        1732121088577,
        0,
        "activate",
        1
      ],
      [
        1732122607802,
        0,
        "activate",
        1
      ],
      [
        1732125140778,
        0,
        "activate",
        1
      ],
      [
        1732155833621,
        0,
        "activate",
        1
      ],
      [
        1732158611902,
        0,
        "activate",
        1
      ]
    ]
  }
}